{
	"storyName": "extras, more will be added! Enjoy (WIP)",
	"difficulties": "",
	"hideFreeplay": false,
	"weekBackground": "philly",
	"freeplayColor": [
		146,
		113,
		253
	],
	"weekBefore": "Secrets",
	"startUnlocked": false,
	"weekCharacters": [
		"",
		"bf",
		"gf"
	],
	"songs": [
		[
			"frostbite",
			"cold-gold",
			[
				205,
				185,
				255
			]
		],
		[
			"score",
			"darnell",
			[
				100,
				70,
				170
			]
		]
	],
	"hideStoryMode": false,
	"weekName": "Secrets-2",
	"hiddenUntilUnlocked": true
}